Workbook

Sheet HotelBookings
A1: Booking_ID | B1: Customer_ID | C1: Guest_Name | D1: Branch_ID | E1: Room_ID | F1: Date_ID | G1: Booking_Date | H1: Checkin_Date | I1: Checkout_Date | J1: Nights | K1: Stay_Type | L1: Booking_Source | M1: Room_Type_Chosen | N1: Booking_Status | O1: Payment_Method | P1: Price_per_Night | Q1: Total_Price | R1: Purpose | S1: Star_Rating
A2: BYD1OSEP7 | B2: C00001 | C2: Ananya Gupta | D2: HB0001 | E2: R00001 | F2: DT0001 | G2: 45828 | H2: 45841 | I2: 45853 | J2: =I2-H2 -> 12 | K2: {=_xlfn.IFS(J2=1,"Day Use",J2<=3,"Short Stay",J2<=7,"Extended Stay",J2>=8,"Long Stay")} -> Long Stay | L2: Expedia | M2: =IF($J2<=3,"Standard",IF($J2<=6,"Deluxe",IF($J2<=10,"Premium","Suite"))) -> Suite | N2: Confirmed | O2: Cash | P2: =IFERROR(VLOOKUP(TRIM(M2),Room!D:H,5,FALSE),5000) -> 12500 | Q2: =P2*J2 -> 150000 | R2: =IF(ISNUMBER(SEARCH("Suite",D2)),"Honeymoon",IF(P2>10000,"Business",IF(P2>5000,"Conference",IF(J2>=8,"Family Vacation","Other")))) -> Business | S2: =IF(M2="Suite",5,IF(M2="Premium",IF(Q2>20000,4,3),IF(M2="Deluxe",IF(Q2>=10000,3,2),IF(M2="Standard",IF(Q2>=5000,2,1),1)))) -> 5
A3: BGOJGP2GB | B3: C00002 | C3: Gaurav Patel | D3: HB0002 | E3: R00002 | F3: DT0002 | G3: 45285 | H3: 45786 | I3: 45797 | J3: =I3-H3 -> 11 | K3: {=_xlfn.IFS(J3=1,"Day Use",J3<=3,"Short Stay",J3<=7,"Extended Stay",J3>=8,"Long Stay")} -> Long Stay | L3: Travel Agent | M3: =IF($J3<=3,"Standard",IF($J3<=6,"Deluxe",IF($J3<=10,"Premium","Suite"))) -> Suite | N3: Confirmed | O3: Credit Card | P3: =IFERROR(VLOOKUP(TRIM(M3),Room!D:H,5,FALSE),5000) -> 12500 | Q3: =P3*J3 -> 137500 | R3: =IF(ISNUMBER(SEARCH("Suite",D3)),"Honeymoon",IF(P3>10000,"Business",IF(P3>5000,"Conference",IF(J3>=8,"Family Vacation","Other")))) -> Business | S3: =IF(M3="Suite",5,IF(M3="Premium",IF(Q3>20000,4,3),IF(M3="Deluxe",IF(Q3>=10000,3,2),IF(M3="Standard",IF(Q3>=5000,2,1),1)))) -> 5
A4: BMHVKCXAL | B4: C00003 | C4: Aisha Joshi | D4: HB0003 | E4: R00003 | F4: DT0003 | G4: 45541 | H4: 45557 | I4: 45563 | J4: =I4-H4 -> 6 | K4: {=_xlfn.IFS(J4=1,"Day Use",J4<=3,"Short Stay",J4<=7,"Extended Stay",J4>=8,"Long Stay")} -> Extended Stay | L4: Expedia | M4: =IF($J4<=3,"Standard",IF($J4<=6,"Deluxe",IF($J4<=10,"Premium","Suite"))) -> Deluxe | N4: Confirmed | O4: Online Transfer | P4: =IFERROR(VLOOKUP(TRIM(M4),Room!D:H,5,FALSE),5000) -> 5400 | Q4: =P4*J4 -> 32400 | R4: =IF(ISNUMBER(SEARCH("Suite",D4)),"Honeymoon",IF(P4>10000,"Business",IF(P4>5000,"Conference",IF(J4>=8,"Family Vacation","Other")))) -> Conference | S4: =IF(M4="Suite",5,IF(M4="Premium",IF(Q4>20000,4,3),IF(M4="Deluxe",IF(Q4>=10000,3,2),IF(M4="Standard",IF(Q4>=5000,2,1),1)))) -> 3
A5: BC2SPVBAX | B5: C00004 | C5: Lucas Iyer | D5: HB0004 | E5: R00004 | F5: DT0004 | G5: 45740 | H5: 45752 | I5: 45757 | J5: =I5-H5 -> 5 | K5: {=_xlfn.IFS(J5=1,"Day Use",J5<=3,"Short Stay",J5<=7,"Extended Stay",J5>=8,"Long Stay")} -> Extended Stay | L5: Corporate | M5: =IF($J5<=3,"Standard",IF($J5<=6,"Deluxe",IF($J5<=10,"Premium","Suite"))) -> Deluxe | N5: Confirmed | O5: Cash | P5: =IFERROR(VLOOKUP(TRIM(M5),Room!D:H,5,FALSE),5000) -> 5400 | Q5: =P5*J5 -> 27000 | R5: =IF(ISNUMBER(SEARCH("Suite",D5)),"Honeymoon",IF(P5>10000,"Business",IF(P5>5000,"Conference",IF(J5>=8,"Family Vacation","Other")))) -> Conference | S5: =IF(M5="Suite",5,IF(M5="Premium",IF(Q5>20000,4,3),IF(M5="Deluxe",IF(Q5>=10000,3,2),IF(M5="Standard",IF(Q5>=5000,2,1),1)))) -> 3
A6: BL6D6PQVP | B6: C00005 | C6: Priya Sharma | D6: HB0005 | E6: R00005 | F6: DT0005 | G6: 45340 | H6: 45853 | I6: 45856 | J6: =I6-H6 -> 3 | K6: {=_xlfn.IFS(J6=1,"Day Use",J6<=3,"Short Stay",J6<=7,"Extended Stay",J6>=8,"Long Stay")} -> Short Stay | L6: Hotel Website | M6: =IF($J6<=3,"Standard",IF($J6<=6,"Deluxe",IF($J6<=10,"Premium","Suite"))) -> Standard | N6: Checked-Out | O6: Debit Card | P6: =IFERROR(VLOOKUP(TRIM(M6),Room!D:H,5,FALSE),5000) -> 3200 | Q6: =P6*J6 -> 9600 | R6: =IF(ISNUMBER(SEARCH("Suite",D6)),"Honeymoon",IF(P6>10000,"Business",IF(P6>5000,"Conference",IF(J6>=8,"Family Vacation","Other")))) -> Other | S6: =IF(M6="Suite",5,IF(M6="Premium",IF(Q6>20000,4,3),IF(M6="Deluxe",IF(Q6>=10000,3,2),IF(M6="Standard",IF(Q6>=5000,2,1),1)))) -> 2
A7: BEMDF3JPH | B7: C00006 | C7: Lucas Joshi | D7: HB0006 | E7: R00006 | F7: DT0006 | G7: 45231 | H7: 45366 | I7: 45376 | J7: =I7-H7 -> 10 | K7: {=_xlfn.IFS(J7=1,"Day Use",J7<=3,"Short Stay",J7<=7,"Extended Stay",J7>=8,"Long Stay")} -> Long Stay | L7: Hotel Website | M7: =IF($J7<=3,"Standard",IF($J7<=6,"Deluxe",IF($J7<=10,"Premium","Suite"))) -> Premium | N7: Confirmed | O7: Online Transfer | P7: =IFERROR(VLOOKUP(TRIM(M7),Room!D:H,5,FALSE),5000) -> 9500 | Q7: =P7*J7 -> 95000 | R7: =IF(ISNUMBER(SEARCH("Suite",D7)),"Honeymoon",IF(P7>10000,"Business",IF(P7>5000,"Conference",IF(J7>=8,"Family Vacation","Other")))) -> Conference | S7: =IF(M7="Suite",5,IF(M7="Premium",IF(Q7>20000,4,3),IF(M7="Deluxe",IF(Q7>=10000,3,2),IF(M7="Standard",IF(Q7>=5000,2,1),1)))) -> 4
A8: BLCQZJ82Z | B8: C00007 | C8: Siddharth Patel | D8: HB0007 | E8: R00007 | F8: DT0007 | G8: 45686 | H8: 45694 | I8: 45703 | J8: =I8-H8 -> 9 | K8: {=_xlfn.IFS(J8=1,"Day Use",J8<=3,"Short Stay",J8<=7,"Extended Stay",J8>=8,"Long Stay")} -> Long Stay | L8: Travel Agent | M8: =IF($J8<=3,"Standard",IF($J8<=6,"Deluxe",IF($J8<=10,"Premium","Suite"))) -> Premium | N8: Confirmed | O8: Wallet | P8: =IFERROR(VLOOKUP(TRIM(M8),Room!D:H,5,FALSE),5000) -> 9500 | Q8: =P8*J8 -> 85500 | R8: =IF(ISNUMBER(SEARCH("Suite",D8)),"Honeymoon",IF(P8>10000,"Business",IF(P8>5000,"Conference",IF(J8>=8,"Family Vacation","Other")))) -> Conference | S8: =IF(M8="Suite",5,IF(M8="Premium",IF(Q8>20000,4,3),IF(M8="Deluxe",IF(Q8>=10000,3,2),IF(M8="Standard",IF(Q8>=5000,2,1),1)))) -> 4
A9: BOHXF823Q | B9: C00008 | C9: Pooja Gupta | D9: HB0008 | E9: R00008 | F9: DT0008 | G9: 45225 | H9: 45607 | I9: 45618 | J9: =I9-H9 -> 11 | K9: {=_xlfn.IFS(J9=1,"Day Use",J9<=3,"Short Stay",J9<=7,"Extended Stay",J9>=8,"Long Stay")} -> Long Stay | L9: Corporate | M9: =IF($J9<=3,"Standard",IF($J9<=6,"Deluxe",IF($J9<=10,"Premium","Suite"))) -> Suite | N9: Confirmed | O9: Wallet | P9: =IFERROR(VLOOKUP(TRIM(M9),Room!D:H,5,FALSE),5000) -> 12500 | Q9: =P9*J9 -> 137500 | R9: =IF(ISNUMBER(SEARCH("Suite",D9)),"Honeymoon",IF(P9>10000,"Business",IF(P9>5000,"Conference",IF(J9>=8,"Family Vacation","Other")))) -> Business | S9: =IF(M9="Suite",5,IF(M9="Premium",IF(Q9>20000,4,3),IF(M9="Deluxe",IF(Q9>=10000,3,2),IF(M9="Standard",IF(Q9>=5000,2,1),1)))) -> 5
A10: B9SU6D143 | B10: C00009 | C10: Sana Verma | D10: HB0009 | E10: R00009 | F10: DT0009 | G10: 45616 | H10: 45803 | I10: 45816 | J10: =I10-H10 -> 13 | K10: {=_xlfn.IFS(J10=1,"Day Use",J10<=3,"Short Stay",J10<=7,"Extended Stay",J10>=8,"Long Stay")} -> Long Stay | L10: Agoda | M10: =IF($J10<=3,"Standard",IF($J10<=6,"Deluxe",IF($J10<=10,"Premium","Suite"))) -> Suite | N10: Confirmed | O10: Wallet | P10: =IFERROR(VLOOKUP(TRIM(M10),Room!D:H,5,FALSE),5000) -> 12500 | Q10: =P10*J10 -> 162500 | R10: =IF(ISNUMBER(SEARCH("Suite",D10)),"Honeymoon",IF(P10>10000,"Business",IF(P10>5000,"Conference",IF(J10>=8,"Family Vacation","Other")))) -> Business | S10: =IF(M10="Suite",5,IF(M10="Premium",IF(Q10>20000,4,3),IF(M10="Deluxe",IF(Q10>=10000,3,2),IF(M10="Standard",IF(Q10>=5000,2,1),1)))) -> 5
A11: B4EU0DBFD | B11: C00010 | C11: Aisha Verma | D11: HB0010 | E11: R00010 | F11: DT0010 | G11: 45339 | H11: 45368 | I11: 45376 | J11: =I11-H11 -> 8 | K11: {=_xlfn.IFS(J11=1,"Day Use",J11<=3,"Short Stay",J11<=7,"Extended Stay",J11>=8,"Long Stay")} -> Long Stay | L11: MakeMyTrip | M11: =IF($J11<=3,"Standard",IF($J11<=6,"Deluxe",IF($J11<=10,"Premium","Suite"))) -> Premium | N11: Confirmed | O11: Debit Card | P11: =IFERROR(VLOOKUP(TRIM(M11),Room!D:H,5,FALSE),5000) -> 9500 | Q11: =P11*J11 -> 76000 | R11: =IF(ISNUMBER(SEARCH("Suite",D11)),"Honeymoon",IF(P11>10000,"Business",IF(P11>5000,"Conference",IF(J11>=8,"Family Vacation","Other")))) -> Conference | S11: =IF(M11="Suite",5,IF(M11="Premium",IF(Q11>20000,4,3),IF(M11="Deluxe",IF(Q11>=10000,3,2),IF(M11="Standard",IF(Q11>=5000,2,1),1)))) -> 4
A12: BTJ98KSFQ | B12: C00011 | C12: Ishaan Patel | D12: HB0011 | E12: R00011 | F12: DT0011 | G12: 45394 | H12: 45444 | I12: 45445 | J12: =I12-H12 -> 1 | K12: {=_xlfn.IFS(J12=1,"Day Use",J12<=3,"Short Stay",J12<=7,"Extended Stay",J12>=8,"Long Stay")} -> Day Use | L12: Travel Agent | M12: =IF($J12<=3,"Standard",IF($J12<=6,"Deluxe",IF($J12<=10,"Premium","Suite"))) -> Standard | N12: Confirmed | O12: Cash | P12: =IFERROR(VLOOKUP(TRIM(M12),Room!D:H,5,FALSE),5000) -> 3200 | Q12: =P12*J12 -> 3200 | R12: =IF(ISNUMBER(SEARCH("Suite",D12)),"Honeymoon",IF(P12>10000,"Business",IF(P12>5000,"Conference",IF(J12>=8,"Family Vacation","Other")))) -> Other | S12: =IF(M12="Suite",5,IF(M12="Premium",IF(Q12>20000,4,3),IF(M12="Deluxe",IF(Q12>=10000,3,2),IF(M12="Standard",IF(Q12>=5000,2,1),1)))) -> 1
A13: BSU2MSGQG | B13: C00012 | C13: Aisha Gupta | D13: HB0012 | E13: R00012 | F13: DT0012 | G13: 45394 | H13: 45512 | I13: 45523 | J13: =I13-H13 -> 11 | K13: {=_xlfn.IFS(J13=1,"Day Use",J13<=3,"Short Stay",J13<=7,"Extended Stay",J13>=8,"Long Stay")} -> Long Stay | L13: Travel Agent | M13: =IF($J13<=3,"Standard",IF($J13<=6,"Deluxe",IF($J13<=10,"Premium","Suite"))) -> Suite | N13: Checked-Out | O13: Debit Card | P13: =IFERROR(VLOOKUP(TRIM(M13),Room!D:H,5,FALSE),5000) -> 12500 | Q13: =P13*J13 -> 137500 | R13: =IF(ISNUMBER(SEARCH("Suite",D13)),"Honeymoon",IF(P13>10000,"Business",IF(P13>5000,"Conference",IF(J13>=8,"Family Vacation","Other")))) -> Business | S13: =IF(M13="Suite",5,IF(M13="Premium",IF(Q13>20000,4,3),IF(M13="Deluxe",IF(Q13>=10000,3,2),IF(M13="Standard",IF(Q13>=5000,2,1),1)))) -> 5
... A2001: BZ5XFGZ73 | B2001: C02000 | C2001: Ritika Patel | D2001: HB2000 | E2001: R02000 | F2001: DT2000 | G2001: 45508 | H2001: 45520 | I2001: 45530 | J2001: =I2001-H2001 -> 10 | K2001: {=_xlfn.IFS(J2001=1,"Day Use",J2001<=3,"Short Stay",J2001<=7,"Extended Stay",J2001>=8,"Long Stay")} -> Long Stay | L2001: Booking.com | M2001: =IF($J2001<=3,"Standard",IF($J2001<=6,"Deluxe",IF($J2001<=10,"Premium","Suite"))) -> Premium | N2001: Checked-In | O2001: Debit Card | P2001: =IFERROR(VLOOKUP(TRIM(M2001),Room!D:H,5,FALSE),5000) -> 9500 | Q2001: =P2001*J2001 -> 95000 | R2001: =IF(ISNUMBER(SEARCH("Suite",D2001)),"Honeymoon",IF(P2001>10000,"Business",IF(P2001>5000,"Conference",IF(J2001>=8,"Family Vacation","Other")))) -> Conference | S2001: =IF(M2001="Suite",5,IF(M2001="Premium",IF(Q2001>20000,4,3),IF(M2001="Deluxe",IF(Q2001>=10000,3,2),IF(M2001="Standard",IF(Q2001>=5000,2,1),1)))) -> 4

Sheet Room
A1: Room_ID | B1: Branch_ID | C1: Room_Number | D1: Room Type | E1: Floor | F1: Room Category | G1: Capacity | H1: Price_per_Night_INR | I1: IsAC
A2: R00001 | B2: HB0001 | C2: 551 | D2: Standard | E2: 7 | F2: =IF(D2="Suite","Premium",IF(D2="Premium","Upper Mid-range",IF(D2="Executive","Mid-range",IF(D2="Deluxe","Economy",IF(D2="Standard","Budget"))))) -> Budget | G2: 4 | H2: 3200 | I2: =IF(H2>=5000,"Yes","No") -> No
A3: R00002 | B3: HB0002 | C3: 309 | D3: Premium | E3: 7 | F3: =IF(D3="Suite","Premium",IF(D3="Premium","Upper Mid-range",IF(D3="Executive","Mid-range",IF(D3="Deluxe","Economy",IF(D3="Standard","Budget"))))) -> Upper Mid-range | G3: 4 | H3: 9500 | I3: =IF(H3>=5000,"Yes","No") -> Yes
A4: R00003 | B4: HB0003 | C4: 756 | D4: Executive | E4: 9 | F4: =IF(D4="Suite","Premium",IF(D4="Premium","Upper Mid-range",IF(D4="Executive","Mid-range",IF(D4="Deluxe","Economy",IF(D4="Standard","Budget"))))) -> Mid-range | G4: 4 | H4: 7200 | I4: =IF(H4>=5000,"Yes","No") -> Yes
A5: R00004 | B5: HB0004 | C5: 767 | D5: Suite | E5: 5 | F5: =IF(D5="Suite","Premium",IF(D5="Premium","Upper Mid-range",IF(D5="Executive","Mid-range",IF(D5="Deluxe","Economy",IF(D5="Standard","Budget"))))) -> Premium | G5: 4 | H5: 12500 | I5: =IF(H5>=5000,"Yes","No") -> Yes
A6: R00005 | B6: HB0005 | C6: 690 | D6: Deluxe | E6: 4 | F6: =IF(D6="Suite","Premium",IF(D6="Premium","Upper Mid-range",IF(D6="Executive","Mid-range",IF(D6="Deluxe","Economy",IF(D6="Standard","Budget"))))) -> Economy | G6: 1 | H6: 5400 | I6: =IF(H6>=5000,"Yes","No") -> Yes
A7: R00006 | B7: HB0006 | C7: 162 | D7: Premium | E7: 7 | F7: =IF(D7="Suite","Premium",IF(D7="Premium","Upper Mid-range",IF(D7="Executive","Mid-range",IF(D7="Deluxe","Economy",IF(D7="Standard","Budget"))))) -> Upper Mid-range | G7: 2 | H7: 9500 | I7: =IF(H7>=5000,"Yes","No") -> Yes
A8: R00007 | B8: HB0007 | C8: 353 | D8: Premium | E8: 6 | F8: =IF(D8="Suite","Premium",IF(D8="Premium","Upper Mid-range",IF(D8="Executive","Mid-range",IF(D8="Deluxe","Economy",IF(D8="Standard","Budget"))))) -> Upper Mid-range | G8: 1 | H8: 9500 | I8: =IF(H8>=5000,"Yes","No") -> Yes
A9: R00008 | B9: HB0008 | C9: 137 | D9: Deluxe | E9: 1 | F9: =IF(D9="Suite","Premium",IF(D9="Premium","Upper Mid-range",IF(D9="Executive","Mid-range",IF(D9="Deluxe","Economy",IF(D9="Standard","Budget"))))) -> Economy | G9: 1 | H9: 5400 | I9: =IF(H9>=5000,"Yes","No") -> Yes
A10: R00009 | B10: HB0009 | C10: 499 | D10: Suite | E10: 5 | F10: =IF(D10="Suite","Premium",IF(D10="Premium","Upper Mid-range",IF(D10="Executive","Mid-range",IF(D10="Deluxe","Economy",IF(D10="Standard","Budget"))))) -> Premium | G10: 2 | H10: 12500 | I10: =IF(H10>=5000,"Yes","No") -> Yes
A11: R00010 | B11: HB0010 | C11: 397 | D11: Suite | E11: 2 | F11: =IF(D11="Suite","Premium",IF(D11="Premium","Upper Mid-range",IF(D11="Executive","Mid-range",IF(D11="Deluxe","Economy",IF(D11="Standard","Budget"))))) -> Premium | G11: 2 | H11: 12500 | I11: =IF(H11>=5000,"Yes","No") -> Yes
A12: R00011 | B12: HB0011 | C12: 548 | D12: Premium | E12: 2 | F12: =IF(D12="Suite","Premium",IF(D12="Premium","Upper Mid-range",IF(D12="Executive","Mid-range",IF(D12="Deluxe","Economy",IF(D12="Standard","Budget"))))) -> Upper Mid-range | G12: 1 | H12: 9500 | I12: =IF(H12>=5000,"Yes","No") -> Yes
A13: R00012 | B13: HB0012 | C13: 685 | D13: Premium | E13: 5 | F13: =IF(D13="Suite","Premium",IF(D13="Premium","Upper Mid-range",IF(D13="Executive","Mid-range",IF(D13="Deluxe","Economy",IF(D13="Standard","Budget"))))) -> Upper Mid-range | G13: 4 | H13: 9500 | I13: =IF(H13>=5000,"Yes","No") -> Yes
... A21: R00020 | B21: HB0020 | C21: 315 | D21: Standard | E21: 5 | F21: =IF(D21="Suite","Premium",IF(D21="Premium","Upper Mid-range",IF(D21="Executive","Mid-range",IF(D21="Deluxe","Economy",IF(D21="Standard","Budget"))))) -> Budget | G21: 3 | H21: 3200 | I21: =IF(H21>=5000,"Yes","No") -> No

Sheet Date
A1: Date_ID | B1: Date | C1: Year | D1: Month | E1: Day | F1: Weekday | G1: Is_Weekend | H1: Quarter
A2: DT0001 | B2: 45946 | C2: 2025 | D2: 10 | E2: 16 | F2: Thursday | G2: FALSE | H2: 4
A3: DT0002 | B3: 45406 | C3: 2024 | D3: 4 | E3: 24 | F3: Wednesday | G3: FALSE | H3: 2
A4: DT0003 | B4: 45317 | C4: 2024 | D4: 1 | E4: 26 | F4: Friday | G4: FALSE | H4: 1
A5: DT0004 | B5: 45573 | C5: 2024 | D5: 10 | E5: 8 | F5: Tuesday | G5: FALSE | H5: 4
A6: DT0005 | B6: 45542 | C6: 2024 | D6: 9 | E6: 7 | F6: Saturday | G6: TRUE | H6: 3
A7: DT0006 | B7: 45520 | C7: 2024 | D7: 8 | E7: 16 | F7: Friday | G7: FALSE | H7: 3
A8: DT0007 | B8: 45434 | C8: 2024 | D8: 5 | E8: 22 | F8: Wednesday | G8: FALSE | H8: 2
A9: DT0008 | B9: 45396 | C9: 2024 | D9: 4 | E9: 14 | F9: Sunday | G9: TRUE | H9: 2
A10: DT0009 | B10: 45984 | C10: 2025 | D10: 11 | E10: 23 | F10: Sunday | G10: TRUE | H10: 4
A11: DT0010 | B11: 45850 | C11: 2025 | D11: 7 | E11: 12 | F11: Saturday | G11: TRUE | H11: 3
A12: DT0011 | B12: 45381 | C12: 2024 | D12: 3 | E12: 30 | F12: Saturday | G12: TRUE | H12: 1
A13: DT0012 | B13: 45896 | C13: 2025 | D13: 8 | E13: 27 | F13: Wednesday | G13: FALSE | H13: 3
... A2001: DT2000 | B2001: 45832 | C2001: 2025 | D2001: 6 | E2001: 24 | F2001: Tuesday | G2001: FALSE | H2001: 2

Sheet Customer
A1: Customer_ID | B1: Guest_Name | C1: Gender | D1: Email | E1: Phone | F1: Country | G1: Loyalty_Status | H1: DOB
A2: C00001 | B2: Priya Singh | C2: Female | D2: priya.singh12@outlook.com | E2: 917197198988 | F2: Germany | G2: Gold | H2: 35179
A3: C00002 | B3: Benjamin Verma | C3: Male | D3: benjamin.verma9@example.com | E3: 917545765374 | F3: Singapore | G3: Silver | H3: 36182
A4: C00003 | B4: Aarav Gupta | C4: Male | D4: aarav.gupta5@yahoo.com | E4: 916217787786 | F4: Australia | G4: Silver | H4: 25267
A5: C00004 | B5: Simran Khan | C5: Female | D5: simran.khan17@gmail.com | E5: 917046680350 | F5: Canada | G5: Silver | H5: 20896
A6: C00005 | B6: Liam Sharma | C6: Male | D6: liam.sharma53@outlook.com | E6: 917700261102 | F6: UAE | G6: None | H6: 35807
A7: C00006 | B7: Shruti Patel | C7: Female | D7: shruti.patel57@example.com | E7: 917973962109 | F7: Canada | G7: Platinum | H7: 33654
A8: C00007 | B8: Sana Verma | C8: Female | D8: sana.verma88@gmail.com | E8: 918799293393 | F8: UK | G8: None | H8: 29917
A9: C00008 | B9: Ananya Joshi | C9: Female | D9: ananya.joshi39@example.com | E9: 919715958985 | F9: Singapore | G9: None | H9: 24039
A10: C00009 | B10: Ritika Verma | C10: Female | D10: ritika.verma4@outlook.com | E10: 917064900549 | F10: Thailand | G10: Gold | H10: 21836
A11: C00010 | B11: Reyansh Iyer | C11: Male | D11: reyansh.iyer11@yahoo.com | E11: 916509019949 | F11: France | G11: Platinum | H11: 20334
A12: C00011 | B12: Lucas Khan | C12: Male | D12: lucas.khan54@example.com | E12: 917977852067 | F12: India | G12: Platinum | H12: 25550
A13: C00012 | B13: Ananya Iyer | C13: Female | D13: ananya.iyer66@example.com | E13: 917554996330 | F13: Canada | G13: None | H13: 27312
... A2001: C02000 | B2001: James Iyer | C2001: Male | D2001: james.iyer45@outlook.com | E2001: 916711350981 | F2001: Thailand | G2001: Silver | H2001: 23939

Sheet HotelBranch
A1: Branch_ID | B1: Branch_Name | C1: City | D1: Country | E1: Address
A2: HB0001 | B2: Metro Inn | C2: Goa | D2: India | E2: 122, Main Street
A3: HB0002 | B3: Grand Hotel | C3: Singapore | D3: IT | E3: 235, MG Road
A4: HB0003 | B4: City Lodge | C4: Toronto | D4: UK | E4: 264, Marine Drive
A5: HB0004 | B5: Royal Suites | C5: Singapore | D5: UK | E5: 181, Station Road
A6: HB0005 | B6: Metro Hotel | C6: Bengaluru | D6: India | E6: 269, Main Street
A7: HB0006 | B7: Grand Residency | C7: Sydney | D7: UK | E7: 199, Main Street
A8: HB0007 | B8: Grand Suites | C8: Bengaluru | D8: India | E8: 177, Station Road
A9: HB0008 | B9: Elite Lodge | C9: London | D9: UAE | E9: 23, Main Street
A10: HB0009 | B10: Heritage Hotel | C10: Bangkok | D10: CA | E10: 94, Station Road
A11: HB0010 | B11: City Inn | C11: Goa | D11: India | E11: 104, MG Road
A12: HB0011 | B12: Grand Suites | C12: Goa | D12: India | E12: 264, Baker Street
... A2001: HB2000 | B2001: Heritage Suites | C2001: Singapore | D2001: SG | E2001: 108, MG Road
